biolink_model/_version.py
biolink_model/datamodel/model.py
biolink_model/datamodel/pydanticmodel_v2.py
biolink_model/prefixmaps/biolink-model-prefix-map.json
biolink_model/prefixmaps/biolink_model_prefix_map.json
biolink_model/prefixmaps/preferred_prefixes_per_class.json
biolink_model/schema/attributes.yaml
biolink_model/schema/biolink_model.yaml
biolink_model/scripts/check_prefix_maps.py
biolink_model/scripts/classprefixes.py
biolink_model/scripts/generate_json.py
biolink_model/scripts/id_prefixes.py
biolink_model/scripts/predicate_review.py
biolink_model/scripts/test_docgen.py
biolink_model/scripts/verify_exclude_list.py
biolink_model-4.3.6.dist-info/METADATA
biolink_model-4.3.6.dist-info/WHEEL
biolink_model-4.3.6.dist-info/entry_points.txt
biolink_model-4.3.6.dist-info/licenses/AUTHORS
biolink_model-4.3.6.dist-info/licenses/LICENSE
biolink_model-4.3.6.dist-info/RECORD
