Metadata-Version: 2.4
Name: biolink-model
Version: 4.3.6
Summary: The Biolink Model is a high-level data model designed to standardize types and relationships in biological knowledgebases.
License: MIT
License-File: AUTHORS
License-File: LICENSE
Author: Chris Mungall
Author-email: cjm@berkeleybop.org
Requires-Python: >=3.9,<4.0
Classifier: License :: OSI Approved :: MIT License
Classifier: Programming Language :: Python :: 3
Classifier: Programming Language :: Python :: 3.9
Classifier: Programming Language :: Python :: 3.10
Classifier: Programming Language :: Python :: 3.11
Classifier: Programming Language :: Python :: 3.12
Classifier: Programming Language :: Python :: 3.13
Classifier: Programming Language :: Python :: 3.14
Provides-Extra: docs
Requires-Dist: beautifulsoup4 (>=4.0.0)
Requires-Dist: click (>8.0.0,<8.2.0)
Requires-Dist: curies (>=0.9.0,<0.10.0)
Requires-Dist: linkml (==1.9.4)
Requires-Dist: linkml-runtime (==1.9.5)
Requires-Dist: path (>=17.0.0,<18.0.0)
Requires-Dist: prefixmaps (>=0.2.3,<0.3.0)
Requires-Dist: pytest (>=8.1.1,<9.0.0)
Requires-Dist: pyyaml (>=6.0.1,<7.0.0)
Requires-Dist: requests (>=2.32.3)
Requires-Dist: stringcase (>=1.2.0,<2.0.0)
Requires-Dist: yamllint (>=1.35.1,<2.0.0)
